scaii/__init__.py
scaii/_internal_/__init__.py
scaii/_internal_/glue.py
scaii/_internal_/libscaii_core.so
scaii/env/__init__.py
scaii/env/actions.py
scaii/env/error.py
scaii/env/explanation.py
scaii/env/state.py
scaii/env/sky_rts/__init__.py
scaii/env/sky_rts/env/__init__.py
scaii/env/sky_rts/env/action.py
scaii/env/sky_rts/env/state.py
scaii/env/sky_rts/env/scenarios/__init__.py
scaii/env/sky_rts/env/scenarios/city_attack.py
scaii/env/sky_rts/env/scenarios/random_towers.py
scaii/env/sky_rts/env/scenarios/tower_example.py
scaii/env/sky_rts/protos/__init__.py
scaii/env/sky_rts/protos/sky_rts_pb2.py
scaii/protos/__init__.py
scaii/protos/cfg_pb2.py
scaii/protos/scaii_pb2.py
scaii/protos/viz_pb2.py
scaii/sky_rts/__init__.py
scaii/sky_rts/env/__init__.py
scaii/sky_rts/env/action.py
scaii/sky_rts/env/state.py
scaii/sky_rts/env/scenarios/__init__.py
scaii/sky_rts/env/scenarios/city_attack.py
scaii/sky_rts/env/scenarios/random_towers.py
scaii/sky_rts/env/scenarios/tower_example.py
scaii/sky_rts/protos/__init__.py
scaii/sky_rts/protos/sky_rts_pb2.py
scaii-0.3.0.dist-info/DESCRIPTION.rst
scaii-0.3.0.dist-info/METADATA
scaii-0.3.0.dist-info/RECORD
scaii-0.3.0.dist-info/WHEEL
scaii-0.3.0.dist-info/metadata.json
scaii-0.3.0.dist-info/top_level.txt
