Metadata-Version: 2.0
Name: scaii
Version: 0.3.0
Summary: Python bindings for https://github.com/SCAII
Home-page: UNKNOWN
Author: Larry Neal
Author-email: nealla@lwneal.com
License: UNKNOWN
Platform: UNKNOWN
